app_confetti/__init__.py
app_confetti/fetch/__init__.py
app_confetti/fetch/aws.py
app_confetti/fetch/dotenv.py
app_confetti/util.py
app_confetti-0.3.0.dist-info/METADATA
app_confetti-0.3.0.dist-info/WHEEL
app_confetti-0.3.0.dist-info/entry_points.txt
app_confetti-0.3.0.dist-info/RECORD
