Metadata-Version: 2.1
Name: app-confetti
Version: 0.3.0
Summary: Environment application configuration
Home-page: https://github.com/EdgyEdgemond/app-confetti/
License: Apache-2.0
Author: Daniel Edgecombe
Author-email: edgy.edgemond@gmail.com
Requires-Python: >=3.8,<4.0
Classifier: License :: OSI Approved :: Apache Software License
Classifier: Programming Language :: Python :: 3
Classifier: Programming Language :: Python :: 3.8
Classifier: Programming Language :: Python :: 3.9
Classifier: Programming Language :: Python :: 3.10
Classifier: Programming Language :: Python :: 3.11
Provides-Extra: aws
Requires-Dist: boto3 (>=1.14.49,<2.0.0) ; extra == "aws"
Requires-Dist: ec2-metadata (>=2.2.0,<3.0.0) ; extra == "aws"
Requires-Dist: python-dotenv (>=1.0.0,<2.0.0)
Project-URL: Repository, https://github.com/EdgyEdgemond/app-confetti/
